{
  "mcpServers": {
    "短信平台 - API 文档": {
      "command": "cmd",
      "args": [
        "/c",
        "npx",
        "-y",
        "apifox-mcp-server@latest",
        "--project-id=7357253"
      ],
      "env": {
        "APIFOX_ACCESS_TOKEN": "APS-rhLjcgfb1y37oMJDzZaA49yVGcf209Oi"
      }
    },
    "playwright": {
      "command": "cmd",
      "args": [
        "/c",
        "npx",
        "-y",
        "@executeautomation/playwright-mcp-server"
      ]
    },
    "chrome-devtools": {
      "command": "cmd",
      "args": [
        "/c",
        "npx",
        "-y",
        "chrome-devtools-mcp@latest"
      ]
    }
  }
}